integrationapi/__init__.py
integrationapi/geolocation.py
integrationapi/payment.py
integrationapi/social_media.py
UnifyAPI-0.1.0.dist-info/METADATA
UnifyAPI-0.1.0.dist-info/WHEEL
UnifyAPI-0.1.0.dist-info/top_level.txt
UnifyAPI-0.1.0.dist-info/RECORD
