Metadata-Version: 2.1
Name: UnifyAPI
Version: 0.1.0
Summary: Python package for integrating with various APIs.
Author: Sirisha Jotheeswaran Padmasekhar
Author-email: sirishajpadmasekhar@gmail.com
Requires-Dist: tweepy
Requires-Dist: paypalrestsdk
Requires-Dist: googlemaps
